thrift_converter/__init__.py
thrift_converter/json_thrift_converter.py
thrift_converter/thrift_converter.py
thrift_converter/thrift_json_converter.py
thrift_converter-0.0.1.dist-info/LICENSE
thrift_converter-0.0.1.dist-info/METADATA
thrift_converter-0.0.1.dist-info/WHEEL
thrift_converter-0.0.1.dist-info/top_level.txt
thrift_converter-0.0.1.dist-info/RECORD
