Metadata-Version: 2.1
Name: thrift-converter
Version: 0.0.1
Summary: Thrift converting tools: json2thrift, thrift2json
Home-page: https://github.com/shiyuan/thrift_converter
Author: Yuan Shi
Author-email: shiyuan404@hotmail.com
License: UNKNOWN
Platform: UNKNOWN
Classifier: Programming Language :: Python :: 3
Classifier: License :: OSI Approved :: MIT License
Classifier: Operating System :: OS Independent
Requires-Dist: ptsd (>=0.1.0)
